<?xml version="1.0" encoding="UTF-8" standalone="yes"?>
<localize xmlns:xsi="http://www.w3.org/2001/XMLSchema-instance">
	<text id="day23_angela_1">長久以來，人類始終渴望創造一個豐饒的世界。</text>
	<text id="day23_angela_2">對他們而言，所謂的「豐饒」究竟意味著什麼？</text>
	<text id="day23_angela_3">難道正因如此，才必須經歷無數衝突與苦痛的交織？</text>
	<text id="day23_angela_4">無數的故事，誕生而後消逝。</text>
	<text id="day23_angela_5">而在此過程中，許多人逐漸失去了信念。</text>
	<text id="day23_angela_6">有人從他們身上看見絕望，有人則看見希望。</text>
	<text id="day23_angela_7">但在某個瞬間，新的文明就此展開。</text>
	<text id="day23_angela_8">萬物在瞬息間被顛覆重組，發生了難以置信的蛻變。</text>
	<text id="day23_angela_9">其後，眾多新技術應運而生。</text>
	<text id="day23_angela_10">作為支撐世界的翼，它們都至少擁有一項「奇點」技術。</text>
	<text id="day23_angela_11">是的，正如最初的人們所期盼的那般，這些都是為了創造豐饒世界而生的技術。</text>
	<text id="day23_angela_12">人們渴望更美好的世界，</text>
	<text id="day23_angela_13">過往難以想像的景象，逐一在眼前浮現。</text>
	<text id="day23_angela_14">然而，這一切是否真的讓所有人都變得豐饒？我們無從知曉。</text>
	<text id="day23_angela_15">唯一能確定的，只有一件事：正是因為這一切，此刻的我，才能夠在您面前，述說這段故事。</text>
</localize>