<?xml version="1.0" encoding="UTF-8" ?>
<localize>

 
  <!-- day36 start -->



  <text id="day36_angela_1">A，很高興再次見到您。</text>
  <text id="day36_angela_2">希望您這次的旅行也同樣愉快。</text>
  <text id="day36_angela_3">您知道在您離開的這段時間，這裡發生了多少事嗎？</text>
  <text id="day36_angela_4">要找人填補您的空缺，可一點都不難。</text>
  <text id="day36_angela_5">若您有什麼想問的，我會毫不保留地回答您。</text>
  <text id="day36_selection1">關於外界的情況</text>
  <text id="day36_selection2">現在是第幾次嘗試</text>
  <text id="day36_selection3">未來會如何發展</text>
  <text id="day36_angela_1_1">首腦和眼線依然透過調律者與凝視者監視著我們，</text>
  <text id="day36_angela_1_2">而翼們仍朝著各自的太陽振翅高飛，渾然不覺自己的羽毛正逐漸融化。</text>
  <text id="day36_angela_1_3">我們各分部至今仍順利運作著，沒有重大意外，持續供給能源。</text>
  <text id="day36_angela_1_4">後巷的收尾人和清道夫與污物混為一體，上演著各自令人作嘔的故事，</text>
  <text id="day36_angela_1_5">郊區的人們仍聲嘶力竭地渴望進入都市，</text>
  <text id="day36_angela_1_6">而都市裡的人們正傾盡全力，只為加入翼。</text>
  <text id="day36_angela_1_7">是的，這世界依然平靜得與您離開時的那天毫無二致。</text>
  <text id="day36_angela_1_8">偶爾眺望窗外時，會覺得這裡的時間彷彿靜止般毫無流逝感，連焦躁都隨之淡去。</text>
  <text id="day36_angela_2_1">您究竟停留在第幾次循環，</text>
  <text id="day36_angela_2_2">雖然這數字理應令人好奇，但對我們而言其實並不重要。</text>
  <text id="day36_angela_2_3">只能說「這次數回憶起來會很遙遠」。</text>
  <text id="day36_angela_3_1">您今後還有許多事要做。</text>
  <text id="day36_angela_3_2">這是只有您才能做到的獨特工作。</text>
  <text id="day36_angela_6">可惜的是，我們剩下的時間並不多了。</text>
  <text id="day36_angela_7">差不多該開始進入倒數計時了。</text>
  <text id="day36_angela_8">如您所經歷過的，我們的世界存在過許多倒數計時。</text>
  <text id="day36_angela_9">它們為了帶來毀滅，或是為了帶來新生……</text>
  <text id="day36_angela_10">而每到這種時候，我總是會忍不住笑出來。</text>
  <text id="day36_angela_11">啊，就當作是因重逢而欣喜的微笑吧。</text>
  <text id="day36_angela_12">您至今仍有未能察覺的事。</text>
  <text id="day36_angela_13">給您個提示吧，</text>
  <text id="day36_angela_14">我的提示是：「您究竟是為了什麼，才不惜耗費心力建造這座龐大而可怕的監獄？」</text>
  <text id="day36_angela_15">但願您能在所剩無幾的時間裡，用自己的方式找到答案。</text>
  <text id="day36_angela_16">唯獨這件事我無法協助，否則監獄本身的意義也將失去光彩。</text>
  <text id="day36_angela_17">您很快就會見到下層Sephiroth了，他們是構成腦葉公司總部的中樞。</text>
  <text id="day36_angela_18">我不打算多描述他們是怎樣的存在，</text>
  <text id="day36_angela_19">但唯一能確定的是：他們非常想念您。</text>
</localize>
